{"cameraMode":{"drawMode":0,"name":"Shaded","section":"Shading Mode"},"sceneLighting":true,"audioPlay":false,"sceneViewState":{"m_AlwaysRefresh":false,"showFog":true,"showSkybox":true,"showFlares":true,"showImageEffects":true,"showParticleSystems":true,"showVisualEffectGraphs":true,"m_FxEnabled":true},"in2DMode":false,"pivot":{"x":-9.752740859985352,"y":-13.23219108581543,"z":9.128545761108399},"rotation":{"x":-0.31401681900024416,"y":0.04611392319202423,"z":-0.015275352634489537,"w":-0.948180615901947},"size":22.253488540649415,"orthographic":false}